allianceauth_oidc/__init__.py
allianceauth_oidc/admin.py
allianceauth_oidc/apps.py
allianceauth_oidc/auth_hooks.py
allianceauth_oidc/auth_provider.py
allianceauth_oidc/models.py
allianceauth_oidc/signals.py
allianceauth_oidc/tasks.py
allianceauth_oidc/urls.py
allianceauth_oidc/views.py
allianceauth_oidc/locale/en/LC_MESSAGES/django.po
allianceauth_oidc/locale/uk/LC_MESSAGES/django.po
allianceauth_oidc/migrations/0001_initial.py
allianceauth_oidc/migrations/0002_alter_allianceauthapplication_options_and_more.py
allianceauth_oidc/migrations/0003_remove_allianceauthapplication_logo_and_more.py
allianceauth_oidc/migrations/0004_allianceauthapplication_allowed_origins_and_more.py
allianceauth_oidc/migrations/__init__.py
allianceauth_oidc/templates/allianceauth_oidc/authorize.html
allianceauth_oidc/templates/allianceauth_oidc/base.html
allianceauth_oidc/templates/allianceauth_oidc/denied.html
allianceauth_oidc/templates/allianceauth_oidc/logout_confirm.html
allianceauth_oidc/tests/__init__.py
allianceauth_oidc/tests/test_access.py
allianceauth_oidc_provider-0.0.1b7.dist-info/LICENSE
allianceauth_oidc_provider-0.0.1b7.dist-info/WHEEL
allianceauth_oidc_provider-0.0.1b7.dist-info/METADATA
allianceauth_oidc_provider-0.0.1b7.dist-info/RECORD
