Metadata-Version: 2.1
Name: allianceauth-oidc-provider
Version: 0.0.1b7
Summary: Alliance Auth OIDC Provider
Author-email: AaronKable <aaronkable@gmail.com>
Classifier: Environment :: Web Environment
Classifier: Framework :: Django
Classifier: Framework :: Django :: 4.0
Classifier: Intended Audience :: Developers
Classifier: License :: OSI Approved :: MIT License
Classifier: Programming Language :: Python
Classifier: Programming Language :: Python :: 3.9
Classifier: Programming Language :: Python :: 3.10
Classifier: Programming Language :: Python :: 3.11
Requires-Dist: allianceauth>=4.0.0
Requires-Dist: django-oauth-toolkit>=3.0.1,<4.0.0
Project-URL: Homepage, https://github.com/Solar-Helix-Independent-Transport/allianceauth-oidc-provider
Project-URL: Source, https://github.com/Solar-Helix-Independent-Transport/allianceauth-oidc-provider
Project-URL: Tracker, https://github.com/Solar-Helix-Independent-Transport/allianceauth-oidc-provider/issues
